README.md
setup.py
cfx_middleware/__init__.py
cfx_middleware/cfx_middleware.py
cfx_middleware.egg-info/PKG-INFO
cfx_middleware.egg-info/SOURCES.txt
cfx_middleware.egg-info/dependency_links.txt
cfx_middleware.egg-info/requires.txt
cfx_middleware.egg-info/top_level.txt
cfx_middleware/__pycache__/cfx_middleware.cpython-311.pyc
cfx_middleware/classes/ChildSerialNumber.py
cfx_middleware/classes/Parameters.py
cfx_middleware/classes/ParserResult.py
cfx_middleware/classes/TestResult.py
cfx_middleware/classes/__pycache__/ChildSerialNumber.cpython-311.pyc
cfx_middleware/classes/__pycache__/Parameters.cpython-311.pyc
cfx_middleware/classes/__pycache__/ParserResult.cpython-311.pyc
cfx_middleware/classes/__pycache__/TestResult.cpython-311.pyc
cfx_middleware/enums/MethodsEnum.py
cfx_middleware/enums/__pycache__/MethodsEnum.cpython-311.pyc
cfx_middleware/exceptions/MethodNotValid.py
cfx_middleware/exceptions/NotDictException.py
cfx_middleware/exceptions/__pycache__/MethodNotValid.cpython-311.pyc
cfx_middleware/exceptions/__pycache__/NotDictException.cpython-311.pyc
cfx_middleware/helpers/utils.py
cfx_middleware/helpers/__pycache__/utils.cpython-311.pyc
cfx_middleware/rabbit/send_rabbit.py
cfx_middleware/rabbit/__pycache__/send_rabbit.cpython-311.pyc