Metadata-Version: 2.1
Name: cfx-middleware
Version: 3.0
Summary: Provide a Middleware between the system and CFX
Home-page: https://dev.azure.com/USI-Applications/USI%20Global%20Development/_git/PCD.Middleware.CFX.Python
Author: Victor Dominguez
Author-email: e-victor_dominguez@usiglobal.com
License: MIT
Classifier: Programming Language :: Python :: 3
Classifier: License :: OSI Approved :: MIT License
Classifier: Operating System :: OS Independent
Requires-Python: >=3
